{"chunk_definitions":[{"row":19,"row_count":1,"visible":true,"expansion_state":0,"options":{"include":false,"engine":"r","label":"setup"},"document_id":"A0C488E3","chunk_id":"ch6dqa1ipwe7s","chunk_label":"setup"},{"row":25,"row_count":1,"visible":true,"expansion_state":0,"options":{"engine":"r","label":"import"},"document_id":"A0C488E3","chunk_id":"c2wav2x8zr21s","chunk_label":"import"},{"row":31,"row_count":1,"visible":true,"expansion_state":0,"options":{"engine":"r","label":"explore-type"},"document_id":"A0C488E3","chunk_id":"c8qpwazfull9p","chunk_label":"explore-type"},{"row":41,"row_count":1,"visible":true,"expansion_state":0,"options":{"engine":"r","label":"unnamed-chunk-2"},"document_id":"A0C488E3","chunk_id":"cvt84pj5cgr5i","chunk_label":"unnamed-chunk-1"}],"doc_write_time":1617164928,"working_dir":null,"default_chunk_options":{}}